__init__.py
sinapsis_llama_cpp/__init__.py
sinapsis_llama_cpp/helpers/__init__.py
sinapsis_llama_cpp/helpers/llama_init_model.py
sinapsis_llama_cpp/helpers/llama_keys.py
sinapsis_llama_cpp/helpers/mcp_constants.py
sinapsis_llama_cpp/helpers/mcp_helpers.py
sinapsis_llama_cpp/templates/__init__.py
sinapsis_llama_cpp/templates/llama4_multimodal.py
sinapsis_llama_cpp/templates/llama4_text_to_text.py
sinapsis_llama_cpp/templates/llama_text_completion.py
sinapsis_llama_cpp/templates/llama_text_completion_mcp.py
sinapsis_llama_cpp/templates/streaming_llama_text_completion.py
sinapsis_llama_cpp-0.3.14.dist-info/licenses/LICENSE
sinapsis_llama_cpp-0.3.14.dist-info/METADATA
sinapsis_llama_cpp-0.3.14.dist-info/WHEEL
sinapsis_llama_cpp-0.3.14.dist-info/top_level.txt
sinapsis_llama_cpp-0.3.14.dist-info/RECORD
