Metadata-Version: 2.4
Name: sinapsis-llama-cpp
Version: 0.3.14
Summary: Sinapsis templates for LLM text completion with LLaMA-CPP
Author-email: SinapsisAI <dev@sinapsis.tech>
Project-URL: Homepage, https://sinapsis.tech
Project-URL: Documentation, https://docs.sinapsis.tech/docs
Project-URL: Tutorials, https://docs.sinapsis.tech/tutorials
Project-URL: Repository, https://github.com/Sinapsis-AI/sinapsis-chatbots.git
Requires-Python: >=3.10
License-File: LICENSE
Requires-Dist: huggingface-hub>=0.32.4
Requires-Dist: llama-cpp-python>=0.3.8
Requires-Dist: llama-index-llms-llama-cpp>=0.4.0
Requires-Dist: ninja>=1.11.1.3
Requires-Dist: pillow>=11.3.0
Requires-Dist: sinapsis>=0.1.1
Requires-Dist: sinapsis-chatbots-base
Provides-Extra: chatbot
Requires-Dist: llvmlite>=0.44.0; extra == "chatbot"
Requires-Dist: sinapsis-chatbots-base[chatbot]; extra == "chatbot"
Provides-Extra: llama-four
Requires-Dist: transformers[torch-vision]>=4.51.0; extra == "llama-four"
Provides-Extra: all
Requires-Dist: sinapsis-llama-cpp[chatbot]; extra == "all"
Requires-Dist: sinapsis-llama-cpp[llama-four]; extra == "all"
Dynamic: license-file
